llama_lime/__init__.py
llama_lime/explainer.py
llama_lime/explorer.py
llama_lime/statistics.py
llama_lime/templates.py
llama_lime-0.1.16.dist-info/LICENSE
llama_lime-0.1.16.dist-info/METADATA
llama_lime-0.1.16.dist-info/WHEEL
llama_lime-0.1.16.dist-info/RECORD
