Metadata-Version: 2.1
Name: llama-lime
Version: 0.1.16
Summary: Explainable AI with Large Language Models
License: MIT
Author: chrisaddy
Author-email: chris.william.addy@gmail.com
Requires-Python: >=3.8.2,<3.12
Classifier: License :: OSI Approved :: MIT License
Classifier: Programming Language :: Python :: 3
Classifier: Programming Language :: Python :: 3.9
Classifier: Programming Language :: Python :: 3.10
Classifier: Programming Language :: Python :: 3.11
Requires-Dist: langchain (>=0.0.267,<0.0.268)
Requires-Dist: lime (>=0.2.0.1,<0.3.0.0)
Requires-Dist: ray (>=2.6.3,<3.0.0)
